{
  "type": "FeatureCollection",
  "features": [
    {
      "type": "Feature",
      "geometry": {
        "type": "Point",
        "coordinates": [
          22.610950,
          88.428644
        ]
      },
      "properties": {
        "title": "44 Bus Stand",
        "description": "more info » Algo. Teacher",
        "marker-size": "large",
        "marker-symbol": "bus"
      }
    }
  ]
}
