{
  "type": "FeatureCollection",
  "features": [
    {
      "type": "Feature",
      "geometry": {
        "type": "Point",
        "coordinates": [
          -77.039882,
          38.898321
        ]
      },
      "properties": {
        "title": "44 Bus Stand",
        "description": "more info » Algo. Teacher",
        "marker-symbol": "bar"
      }
    }
  ]
}
